MANIFEST.in
README.md
setup.py
fortnite_replay_reader.egg-info/PKG-INFO
fortnite_replay_reader.egg-info/SOURCES.txt
fortnite_replay_reader.egg-info/dependency_links.txt
fortnite_replay_reader.egg-info/not-zip-safe
fortnite_replay_reader.egg-info/requires.txt
fortnite_replay_reader.egg-info/top_level.txt
ray/__init__.py
ray/exceptions.py
ray/logging.py
ray/models.py
ray/reader.py