Metadata-Version: 2.1
Name: fortnite-replay-reader
Version: 0.3.0
Summary: Parse fortnite .replay files
Home-page: http://github.com/Shiqan/fortnite-replay-reader
Author: Shiqan
License: MIT
Keywords: fortnite replay reader ray
Platform: UNKNOWN
Classifier: Development Status :: 3 - Alpha
Classifier: Intended Audience :: Developers
Classifier: License :: OSI Approved :: MIT License
Classifier: Programming Language :: Python :: 3.7
